fullcalendar_hj3415/.DS_Store
fullcalendar_hj3415/__init__.py
fullcalendar_hj3415/admin.py
fullcalendar_hj3415/apps.py
fullcalendar_hj3415/models.py
fullcalendar_hj3415/tests.py
fullcalendar_hj3415/views.py
fullcalendar_hj3415/migrations/0001_initial.py
fullcalendar_hj3415/migrations/__init__.py
fullcalendar_hj3415/static/fullcalendar_hj3415/fullcalendar4/packages/bootstrap/LICENSE.txt
fullcalendar_hj3415/static/fullcalendar_hj3415/fullcalendar4/packages/bootstrap/README.md
fullcalendar_hj3415/static/fullcalendar_hj3415/fullcalendar4/packages/bootstrap/main.css
fullcalendar_hj3415/static/fullcalendar_hj3415/fullcalendar4/packages/bootstrap/main.d.ts
fullcalendar_hj3415/static/fullcalendar_hj3415/fullcalendar4/packages/bootstrap/main.esm.js
fullcalendar_hj3415/static/fullcalendar_hj3415/fullcalendar4/packages/bootstrap/main.js
fullcalendar_hj3415/static/fullcalendar_hj3415/fullcalendar4/packages/bootstrap/main.min.css
fullcalendar_hj3415/static/fullcalendar_hj3415/fullcalendar4/packages/bootstrap/main.min.js
fullcalendar_hj3415/static/fullcalendar_hj3415/fullcalendar4/packages/bootstrap/package.json
fullcalendar_hj3415/static/fullcalendar_hj3415/fullcalendar4/packages/core/LICENSE.txt
fullcalendar_hj3415/static/fullcalendar_hj3415/fullcalendar4/packages/core/README.md
fullcalendar_hj3415/static/fullcalendar_hj3415/fullcalendar4/packages/core/locales-all.js
fullcalendar_hj3415/static/fullcalendar_hj3415/fullcalendar4/packages/core/locales-all.min.js
fullcalendar_hj3415/static/fullcalendar_hj3415/fullcalendar4/packages/core/main.css
fullcalendar_hj3415/static/fullcalendar_hj3415/fullcalendar4/packages/core/main.d.ts
fullcalendar_hj3415/static/fullcalendar_hj3415/fullcalendar4/packages/core/main.esm.js
fullcalendar_hj3415/static/fullcalendar_hj3415/fullcalendar4/packages/core/main.js
fullcalendar_hj3415/static/fullcalendar_hj3415/fullcalendar4/packages/core/main.min.css
fullcalendar_hj3415/static/fullcalendar_hj3415/fullcalendar4/packages/core/main.min.js
fullcalendar_hj3415-0.2.0.dist-info/WHEEL
fullcalendar_hj3415-0.2.0.dist-info/METADATA
fullcalendar_hj3415-0.2.0.dist-info/RECORD
